knotifier/__init__.py
knotifier/notifier.py
knotifier/task.py
knotifier-0.0.2.dist-info/LICENSE
knotifier-0.0.2.dist-info/METADATA
knotifier-0.0.2.dist-info/WHEEL
knotifier-0.0.2.dist-info/top_level.txt
knotifier-0.0.2.dist-info/RECORD
